FINAL/UART1_tester.v
module UART1_tester(
    output reg clk,
    output reg rst,
    output reg idle_bit,
    output reg start_bit,
    output reg [7:0] tx1,
    output reg stop_bit,
    output reg load,
    input wire serial_out,
    input wire parallel_in_active
);

    always begin
        #5 clk = ~clk; 
    end

    initial begin
        clk = 1;
        rst = 1;
        load = 0;
        idle_bit = 1;
        start_bit = 1;
        tx1 = 8'b00000000;
        stop_bit = 0;

        #10 rst = 0;

        #10 idle_bit = 0; 
        start_bit = 0; 
        #10 start_bit = 1; load = 1; tx1 = 8'b10111010; 
        #10 load = 0; #80 tx1 = 8'b0; 
        #10 stop_bit = 1; 
        #10 idle_bit = 1; stop_bit = 0; 
        #200 $finish;
    end

endmodule

FINAL/UART1_dut.v
module UART1_dut(
    input wire clk,
    input wire rst,
    input wire load,
    input wire idle_bit,
    input wire start_bit,
    input wire [7:0] tx1,
    input wire stop_bit,
    output reg serial_out,
    output reg parallel_in_active
);

    localparam IDLE = 3'b000,
               START = 3'b001,
               DATA = 3'b010,
               PARITY = 3'b011,
               STOP = 3'b100;

    reg [2:0] state, next_state;
    reg [7:0] data_register; 
    reg [3:0] contador;

    reg [7:0] shift_register; 
    reg [3:0] bit_counter;    
    reg serial_out_ready;   

    reg parity_bit;    
    reg temp_parity_bit; // Registro auxiliar para la paridad

    // Estado actual y lógica secuencial
    
    always @(posedge clk or posedge rst) begin
        if (rst) begin
            state <= IDLE;
            serial_out <= 1'b0;
            data_register <= 8'b0;
            contador <= 4'b0;
            parity_bit <= 1'b0;
            temp_parity_bit <= 1'b0;
        end else begin
            state <= next_state;
/*
            case (state)
                IDLE: serial_out <= 1'b1; 
                START: serial_out <= 1'b0; 
                DATA: begin
                    serial_out <= data_register[0]; // BMS primero 
                    data_register <= {1'b0, data_register[7:1]}; // Shift right
                end
                PARITY: serial_out <= parity_bit;
                STOP: serial_out <= 1'b0; 
            endcase
*/
        end 
    end

    // PISO
    always @(posedge clk or posedge rst) begin
        if (rst) begin
            shift_register <= 8'b0;
            serial_out <= 1'b0;
            bit_counter <= 4'b0;
            parallel_in_active <= 1'b0;
            serial_out_ready <= 1'b0; 
        end else if (load) begin
            
            shift_register <= tx1;
            parallel_in_active <= 1'b1; 
            bit_counter <= 4'b0;        
            serial_out <= 1'b0;         
            serial_out_ready <= 1'b0;   
        end else if (parallel_in_active) begin
            
            bit_counter <= bit_counter + 1;
            
            if (bit_counter == 4'b0111) begin
                parallel_in_active <= 1'b0;  
                serial_out_ready <= 1'b1;    
            end
        end else if (serial_out_ready) begin
            
            serial_out <= shift_register[0];
            shift_register <= shift_register >> 1; 
            bit_counter <= bit_counter + 1;

            
            if (bit_counter == 4'b0111) begin
                serial_out_ready <= 1'b0; 
                bit_counter <= 4'b0;      
            end
        end
    end


    
    // Lógica combinacional de transición de estados
    always @(*) begin
        next_state = state;

        case (state)
            IDLE: if (!idle_bit) next_state = START;
            START: if (!start_bit || !idle_bit) next_state = DATA;
            DATA: if (contador == 8) next_state = PARITY;
            PARITY: next_state = STOP;
            STOP: next_state = IDLE;
        endcase
    end

    // Cálculo de paridad
    always @(posedge clk or posedge rst) begin
        if (rst) begin
            temp_parity_bit <= 1'b0;
        end else if (state == DATA && contador == 0) begin
            temp_parity_bit <= ^tx1;
        end
    end

    // Activación de parity_bit en el estado PARITY
    always @(*) begin
        if (state == PARITY) begin
            parity_bit = temp_parity_bit; 
        end else begin
            parity_bit = 1'b0; 
        end
    end

    // Contador para DATA
    always @(posedge clk or posedge rst) begin
        if (rst) begin
            contador <= 4'b0;
        end else if (state == DATA) begin
            if (contador < 8) contador <= contador + 1;
        end else begin
            contador <= 4'b0;
        end
    end

endmodule

FINAL/UART1_tb.v
`include "UART1_dut.v"
`include "UART1_tester.v"

module UART1_tb;

    wire clk;
    wire rst;
    wire load;
    wire idle_bit;
    wire start_bit;
    wire [7:0] tx1;
    wire stop_bit;
    wire serial_out;
    wire parallel_in_active;

    UART1_dut dut (
        .clk(clk),
        .rst(rst),
        .idle_bit(idle_bit),
        .start_bit(start_bit),
        .tx1(tx1),
        .stop_bit(stop_bit),
        .serial_out(serial_out),
        .load(load),
        .parallel_in_active(parallel_in_active)
    );

    UART1_tester tester (
        .clk(clk),
        .rst(rst),
        .idle_bit(idle_bit),
        .start_bit(start_bit),
        .tx1(tx1),
        .stop_bit(stop_bit),
        .serial_out(serial_out),
        .load(load),
        .parallel_in_active(parallel_in_active)
    );

    initial begin
        $dumpfile("UART1_tb.vcd");
        $dumpvars(0, UART1_tb);
    end

endmodule

FINAL/UART1_tb.vcd
$date
	Sun Dec  1 04:27:10 2024
$end
$version
	Icarus Verilog
$end
$timescale
	1s
$end
$scope module UART1_tb $end
$var wire 8 ! tx1 [7:0] $end
$var wire 1 " stop_bit $end
$var wire 1 # start_bit $end
$var wire 1 $ serial_out $end
$var wire 1 % rst $end
$var wire 1 & parallel_in_active $end
$var wire 1 ' load $end
$var wire 1 ( idle_bit $end
$var wire 1 ) clk $end
$scope module dut $end
$var wire 8 * tx1 [7:0] $end
$var wire 1 " stop_bit $end
$var wire 1 # start_bit $end
$var wire 1 % rst $end
$var wire 1 ' load $end
$var wire 1 ( idle_bit $end
$var wire 1 ) clk $end
$var parameter 3 + DATA $end
$var parameter 3 , IDLE $end
$var parameter 3 - PARITY $end
$var parameter 3 . START $end
$var parameter 3 / STOP $end
$var reg 4 0 bit_counter [3:0] $end
$var reg 4 1 contador [3:0] $end
$var reg 8 2 data_register [7:0] $end
$var reg 3 3 next_state [2:0] $end
$var reg 1 & parallel_in_active $end
$var reg 1 4 parity_bit $end
$var reg 1 $ serial_out $end
$var reg 1 5 serial_out_ready $end
$var reg 8 6 shift_register [7:0] $end
$var reg 3 7 state [2:0] $end
$var reg 1 8 temp_parity_bit $end
$upscope $end
$scope module tester $end
$var wire 1 & parallel_in_active $end
$var wire 1 $ serial_out $end
$var reg 1 ) clk $end
$var reg 1 ( idle_bit $end
$var reg 1 ' load $end
$var reg 1 % rst $end
$var reg 1 # start_bit $end
$var reg 1 " stop_bit $end
$var reg 8 9 tx1 [7:0] $end
$upscope $end
$upscope $end
$enddefinitions $end
$comment Show the parameter values. $end
$dumpall
b100 /
b1 .
b11 -
b0 ,
b10 +
$end
#0
$dumpvars
b0 9
08
b0 7
b0 6
05
04
b0 3
b0 2
b0 1
b0 0
b0 *
1)
1(
0'
0&
1%
0$
1#
0"
b0 !
$end
#5
0)
#10
1)
0%
#15
0)
#20
b1 7
b10 3
1)
0#
0(
#25
0)
#30
1&
b10111010 6
b10 7
b10 3
1)
b10111010 !
b10111010 *
b10111010 9
1'
1#
#35
0)
#40
b1 0
18
b1 1
1)
0'
#45
0)
#50
b10 1
b10 0
1)
#55
0)
#60
b11 0
b11 1
1)
#65
0)
#70
b100 1
b100 0
1)
#75
0)
#80
b101 0
b101 1
1)
#85
0)
#90
b110 1
b110 0
1)
#95
0)
#100
b111 0
b111 1
1)
#105
0)
#110
b11 3
b1000 1
15
0&
b1000 0
1)
#115
0)
#120
14
b100 3
b11 7
b1001 0
b1011101 6
1)
b0 !
b0 *
b0 9
#125
0)
#130
04
b0 3
b0 1
b1010 0
b101110 6
1$
b100 7
1)
1"
#135
0)
#140
b0 7
b1011 0
b10111 6
0$
b0 3
1)
0"
1(
#145
0)
#150
b1100 0
b1011 6
1$
1)
#155
0)
#160
b1101 0
b101 6
1)
#165
0)
#170
b1110 0
b10 6
1)
#175
0)
#180
b1111 0
b1 6
0$
1)
#185
0)
#190
b0 0
b0 6
1$
1)
#195
0)
#200
b1 0
0$
1)
#205
0)
#210
b10 0
1)
#215
0)
#220
b11 0
1)
#225
0)
#230
b100 0
1)
#235
0)
#240
b101 0
1)
#245
0)
#250
b110 0
1)
#255
0)
#260
b111 0
1)
#265
0)
#270
05
b0 0
1)
