FINAL/UART1_tester.v
module UART1_tester(
    output reg clk_uart,
    output reg clk_sis,
    output reg rst,
    output reg start_bit,
    output reg [7:0] data_in,
    output reg stop_bit,
    input wire tx1
);

    // Generador de clk_uart (frecuencia base)
    always begin
        #5 clk_uart = ~clk_uart; // clk_uart cambia cada 5 unidades de tiempo
    end

    // Generador de clk_sis (doble de la frecuencia de clk_uart)
    always begin
        #2.5 clk_sis = ~clk_sis; // clk_sis cambia cada 10 unidades de tiempo
    end

    // PRUEBA UART1:
    initial begin
        // Se inicializan los valores de prueba
        clk_sis = 1;
        clk_uart = 1;
        rst = 1;
        start_bit = 1;
        data_in = 8'b00000000;
        stop_bit = 0;

        // Cambios de datos
        #10 rst = 0;
        start_bit = 0; 
        #10 start_bit = 1; data_in = 8'b01011011; 
        #90 data_in = 8'b0; 
        stop_bit = 1;
        #10 stop_bit = 0; 
        #10 rst = 1;
        #10 rst = 0;
        #200 $finish;
        
    end

endmodule

FINAL/UART1_dut.v
module UART1_dut(
    input wire clk_uart,                               // Reloj principal del módulo UART
    input wire clk_sis,                                // Reloj del sistema 
    input wire rst,                                    
    input wire start_bit,                              // Indica el inicio de la transmisión
    input wire [7:0] data_in,                          // Dato de 8 bits a transmitir en serie
    input wire stop_bit,                               // Indica el fin de la transmisión
    input wire rx1,                                    // Linea de recepcion serie desde UART2
    output reg tx1                                     // Línea de transmisión serie hacia UART2
);

    // Declaración de los estados del transmisor UART
    localparam IDLE = 3'b000,                       
               START = 3'b001,                      
               DATA = 3'b010,                       
               PARITY = 3'b011,                     
               STOP = 3'b100;                       

    reg [2:0] state, next_state;                       // Estado actual y siguiente
    reg idle_bit;                                      // Bandera para indicar si el sistema está en reposo
    reg [3:0] cnt_bits, next_cnt_bits;                 // Contador para rastrear los bits transmitidos
    reg parity_bit;                                    // Almacena el bit de paridad calculado

    // **Lógica Secuencial
    always @(posedge clk_uart or posedge rst) begin
        if (rst) begin
            // Reinicia todos los registros al estado inicial
            state        <= IDLE;                      // Comienza en el estado `IDLE`
            tx1          <= 1'b1;                      // Línea en alto (reposo)
            parity_bit   <= 1'b0;                      // Inicializa el bit de paridad
            cnt_bits     <= 4'b0;                      // Reinicia el contador de bits
        end else begin
            // Actualización de los registros en función de la lógica combinacional
            state        <= next_state;               
            cnt_bits     <= next_cnt_bits;            
        end
    end

    // **Lógica Combinacional
    always @(*) begin
        // Valores predeterminados para evitar latches
        next_state = state;                           // Por defecto, el estado no cambia
        next_cnt_bits = cnt_bits;                     // Por defecto, el contador no cambia
        idle_bit = 1;                                 // `idle_bit` indica reposo salvo en `IDLE` 

        // Máquina de estados finita (FSM) //Se va armando la señal de tx1.
        case (state)
            IDLE: begin
                idle_bit = 0;                         
                tx1 = 1'b1;                           
                if (!idle_bit) 
                    next_state = START;              
            end

            START: begin
                tx1 = 1'b0;             
                next_state = DATA;      
            end

            DATA: begin
                // Transmite los bits de datos en serie uno por uno
                tx1 = data_in[cnt_bits];    // Selecciona el bit correspondiente LSB
                next_cnt_bits = cnt_bits + 1; 
                if (cnt_bits == 7)          // Si todos los bits han sido transmitidos
                    next_state = PARITY;    
            end

            PARITY: begin
                parity_bit = ^data_in;      // Calcula la paridad XOR de los datos
                tx1 = parity_bit;           // Transmite el bit de paridad
                next_state = STOP;          // Cambia al estado de parada
            end

            STOP: begin
                tx1 = 1'b1;                 // Transmite el bit de parada (alto)
                if (stop_bit) 
                    next_state = IDLE;      
            end
        endcase
    end

endmodule

FINAL/UART1_tb.v
`include "UART1_dut.v"
`include "UART1_tester.v"

module UART1_tb;

    wire clk_uart;
    wire clk_sis;
    wire rst;
    wire load;
    wire start_bit;
    wire [7:0] data_in;
    wire stop_bit;
    wire tx1;

    UART1_dut dut (
        .clk_uart(clk_uart),
        .clk_sis(clk_sis),
        .rst(rst),
        .start_bit(start_bit),
        .data_in(data_in),
        .stop_bit(stop_bit),
        .tx1(tx1)
    );

    UART1_tester tester (
        .clk_uart(clk_uart),
        .clk_sis(clk_sis),
        .rst(rst),
        .start_bit(start_bit),
        .data_in(data_in),
        .stop_bit(stop_bit),
        .tx1(tx1)
    );

    initial begin
        $dumpfile("UART1_tb.vcd");
        $dumpvars(0, UART1_tb);
    end

endmodule

FINAL/UART1_tb.vcd
$date
	Sun Dec  1 17:34:48 2024
$end
$version
	Icarus Verilog
$end
$timescale
	1s
$end
$scope module UART1_tb $end
$var wire 1 ! tx1 $end
$var wire 1 " stop_bit $end
$var wire 1 # start_bit $end
$var wire 1 $ rst $end
$var wire 8 % data_in [7:0] $end
$var wire 1 & clk_uart $end
$var wire 1 ' clk_sis $end
$scope module dut $end
$var wire 1 ( rx1 $end
$var wire 1 " stop_bit $end
$var wire 1 # start_bit $end
$var wire 1 $ rst $end
$var wire 8 ) data_in [7:0] $end
$var wire 1 & clk_uart $end
$var wire 1 ' clk_sis $end
$var parameter 3 * DATA $end
$var parameter 3 + IDLE $end
$var parameter 3 , PARITY $end
$var parameter 3 - START $end
$var parameter 3 . STOP $end
$var reg 4 / cnt_bits [3:0] $end
$var reg 1 0 idle_bit $end
$var reg 4 1 next_cnt_bits [3:0] $end
$var reg 3 2 next_state [2:0] $end
$var reg 1 3 parity_bit $end
$var reg 3 4 state [2:0] $end
$var reg 1 ! tx1 $end
$upscope $end
$scope module tester $end
$var wire 1 ! tx1 $end
$var reg 1 ' clk_sis $end
$var reg 1 & clk_uart $end
$var reg 8 5 data_in [7:0] $end
$var reg 1 $ rst $end
$var reg 1 # start_bit $end
$var reg 1 " stop_bit $end
$upscope $end
$upscope $end
$enddefinitions $end
$comment Show the parameter values. $end
$dumpall
b100 .
b1 -
b11 ,
b0 +
b10 *
$end
#0
$dumpvars
b0 5
b0 4
03
b1 2
b0 1
00
b0 /
b0 )
z(
1'
1&
b0 %
1$
1#
0"
1!
$end
#3
0'
#5
0&
#6
1'
#9
0'
#10
b10 2
0!
10
b1 4
1&
0#
0$
#12
1'
#15
0'
0&
#18
1'
#20
b1 1
1!
b10 4
b10 2
1&
b1011011 %
b1011011 )
b1011011 5
1#
#21
0'
#24
1'
#25
0&
#27
0'
#30
b10 1
b1 /
1'
1&
#33
0'
#35
0&
#36
1'
#39
0'
#40
b11 1
0!
b10 /
1&
#42
1'
#45
0'
0&
#48
1'
#50
b100 1
1!
b11 /
1&
#51
0'
#54
1'
#55
0&
#57
0'
#60
b101 1
b100 /
1'
1&
#63
0'
#65
0&
#66
1'
#69
0'
#70
b110 1
0!
b101 /
1&
#72
1'
#75
0'
0&
#78
1'
#80
b111 1
1!
b110 /
1&
#81
0'
#84
1'
#85
0&
#87
0'
#90
b11 2
b1000 1
0!
b111 /
1'
1&
#93
0'
#95
0&
#96
1'
#99
0'
#100
b100 2
1!
13
b1000 /
b11 4
1&
#102
1'
#105
0'
0&
#108
1'
#110
b100 4
1!
03
b0 2
1&
1"
b0 %
b0 )
b0 5
#111
0'
#114
1'
#115
0&
#117
0'
#120
b100 2
1'
1&
0"
#123
0'
#125
0&
#126
1'
#129
0'
#130
00
b0 1
b1 2
b0 /
b0 4
1&
1$
#132
1'
#135
0'
0&
#138
1'
#140
b10 2
0!
10
b1 4
1&
0$
#141
0'
#144
1'
#145
0&
#147
0'
#150
b1 1
b10 4
1'
1&
#153
0'
#155
0&
#156
1'
#159
0'
#160
b10 1
b1 /
1&
#162
1'
#165
0'
0&
#168
1'
#170
b11 1
b10 /
1&
#171
0'
#174
1'
#175
0&
#177
0'
#180
b100 1
b11 /
1'
1&
#183
0'
#185
0&
#186
1'
#189
0'
#190
b101 1
b100 /
1&
#192
1'
#195
0'
0&
#198
1'
#200
b110 1
b101 /
1&
#201
0'
#204
1'
#205
0&
#207
0'
#210
b111 1
b110 /
1'
1&
#213
0'
#215
0&
#216
1'
#219
0'
#220
b11 2
b1000 1
b111 /
1&
#222
1'
#225
0'
0&
#228
1'
#230
b100 2
b1000 /
b11 4
1&
#231
0'
#234
1'
#235
0&
#237
0'
#240
1!
b100 4
1'
1&
