FINAL/UART1_tester.v
module UART1_tester(
    output reg clk,
    output reg rst,
    // output reg idle_bit,
    output reg start_bit,
    output reg [7:0] data_in,
    output reg stop_bit,
    output reg load,
    input wire tx1,
    input wire parallel_in_active
);

    always begin
        #5 clk = ~clk; 
    end

    initial begin
        clk = 1;
        rst = 1;
        load = 0;
        // idle_bit = 1;
        start_bit = 1;
        data_in = 8'b00000000;
        stop_bit = 0;

        #10 rst = 0;

        // #10 idle_bit = 0; 
        start_bit = 0; 
        #10 start_bit = 1; load = 1; data_in = 8'b01011011; 
        #10 load = 0; #80 data_in = 8'b0; 
        stop_bit = 1;
        // #10 idle_bit = 1; stop_bit = 0; 
        #10 stop_bit = 0; 
        #10 rst = 1;
        #10 rst = 0;
        #200 $finish;
        
    end

endmodule

FINAL/UART1_dut.v
module UART1_dut(
    input wire clk,
    input wire rst,
    input wire load,
    input wire start_bit,
    input wire [7:0] data_in,
    input wire stop_bit,
    output reg tx1,
    output reg parallel_in_active
);

    localparam IDLE = 3'b000,
               START = 3'b001,
               DATA = 3'b010,
               PARITY = 3'b011,
               STOP = 3'b100;

    reg [2:0] state, next_state;
    reg [7:0] data_register; 
    reg [3:0] contador;

    reg [7:0] shift_register; 
    reg [3:0] bit_counter;    
    reg tx1_ready, idle_bit;   
    reg [3:0] cnt_bits, next_cnt_bits;
    reg parity_bit;    
    reg temp_parity_bit; // Registro auxiliar para la paridad

    // Lógica Secuencial
    always @(posedge clk or posedge rst) begin
        if (rst) begin
            state           <= IDLE;
            tx1             <= 1'b0;
            data_register   <= 8'b0;
            contador        <= 4'b0;
            parity_bit      <= 1'b0;
            temp_parity_bit <= 1'b0;
            cnt_bits        <= 0;
            bit_counter     <= 0;
        end else begin
            state           <= next_state;
            cnt_bits        <= next_cnt_bits;
        end 
    end

// Lógica Combinacional
always @(*) begin
    // Sosteniendo valores de FF.
    next_state = state;
    next_cnt_bits = cnt_bits;
    
    // Valores de salida por defecto.
    idle_bit = 1; // idle_bit = 1 a menos que estemos en el estado IDLE
    // Casos para cada estado.
    case(state)
        IDLE: begin
            idle_bit  = 0; // idle_bit = 1 a menos que estemos en el estado IDLE
            tx1       = 1'b1;
            if (!idle_bit) next_state = START;
        end
        START: begin
            tx1        = 1'b0;
            next_state = DATA;
        end
        DATA: begin
            tx1 = data_in[0 + cnt_bits];
            next_cnt_bits = cnt_bits + 1;
            if (cnt_bits == 7) begin
                next_state  = PARITY;
                
            end
        end
        PARITY: begin
            parity_bit   = ^data_in;
            tx1          = parity_bit;
            next_state   = STOP;
        end

        STOP: begin
            if (stop_bit) tx1 = 1'b1;
            tx1 = 1;
            next_state = IDLE;
        end
        //default: next_state = IDLE;
        
    endcase
end

endmodule

FINAL/UART1_tb.v
`include "UART1_dut.v"
`include "UART1_tester.v"

module UART1_tb;

    wire clk;
    wire rst;
    wire load;
    // wire idle_bit;
    wire start_bit;
    wire [7:0] data_in;
    wire stop_bit;
    wire tx1;
    wire parallel_in_active;

    UART1_dut dut (
        .clk(clk),
        .rst(rst),
        // .idle_bit(idle_bit),
        .start_bit(start_bit),
        .data_in(data_in),
        .stop_bit(stop_bit),
        .tx1(tx1),
        .load(load),
        .parallel_in_active(parallel_in_active)
    );

    UART1_tester tester (
        .clk(clk),
        .rst(rst),
        // .idle_bit(idle_bit),
        .start_bit(start_bit),
        .data_in(data_in),
        .stop_bit(stop_bit),
        .tx1(tx1),
        .load(load),
        .parallel_in_active(parallel_in_active)
    );

    initial begin
        $dumpfile("UART1_tb.vcd");
        $dumpvars(0, UART1_tb);
    end

endmodule

FINAL/UART1_tb.vcd
$date
	Sun Dec  1 16:10:23 2024
$end
$version
	Icarus Verilog
$end
$timescale
	1s
$end
$scope module UART1_tb $end
$var wire 1 ! tx1 $end
$var wire 1 " stop_bit $end
$var wire 1 # start_bit $end
$var wire 1 $ rst $end
$var wire 1 % parallel_in_active $end
$var wire 1 & load $end
$var wire 8 ' data_in [7:0] $end
$var wire 1 ( clk $end
$scope module dut $end
$var wire 1 " stop_bit $end
$var wire 1 # start_bit $end
$var wire 1 $ rst $end
$var wire 1 & load $end
$var wire 8 ) data_in [7:0] $end
$var wire 1 ( clk $end
$var parameter 3 * DATA $end
$var parameter 3 + IDLE $end
$var parameter 3 , PARITY $end
$var parameter 3 - START $end
$var parameter 3 . STOP $end
$var reg 4 / bit_counter [3:0] $end
$var reg 4 0 cnt_bits [3:0] $end
$var reg 4 1 contador [3:0] $end
$var reg 8 2 data_register [7:0] $end
$var reg 1 3 idle_bit $end
$var reg 4 4 next_cnt_bits [3:0] $end
$var reg 3 5 next_state [2:0] $end
$var reg 1 % parallel_in_active $end
$var reg 1 6 parity_bit $end
$var reg 3 7 state [2:0] $end
$var reg 1 8 temp_parity_bit $end
$var reg 1 ! tx1 $end
$upscope $end
$scope module tester $end
$var wire 1 % parallel_in_active $end
$var wire 1 ! tx1 $end
$var reg 1 ( clk $end
$var reg 8 9 data_in [7:0] $end
$var reg 1 & load $end
$var reg 1 $ rst $end
$var reg 1 # start_bit $end
$var reg 1 " stop_bit $end
$upscope $end
$upscope $end
$enddefinitions $end
$comment Show the parameter values. $end
$dumpall
b100 .
b1 -
b11 ,
b0 +
b10 *
$end
#0
$dumpvars
b0 9
08
b0 7
06
b1 5
b0 4
03
b0 2
b0 1
b0 0
b0 /
b0 )
1(
b0 '
0&
x%
1$
1#
0"
1!
$end
#5
0(
#10
b10 5
0!
13
b1 7
1(
0#
0$
#15
0(
#20
b1 4
1!
b10 7
b10 5
1(
b1011011 '
b1011011 )
b1011011 9
1&
1#
#25
0(
#30
b10 4
b1 0
1(
0&
#35
0(
#40
b11 4
0!
b10 0
1(
#45
0(
#50
b100 4
1!
b11 0
1(
#55
0(
#60
b101 4
b100 0
1(
#65
0(
#70
b110 4
0!
b101 0
1(
#75
0(
#80
b111 4
1!
b110 0
1(
#85
0(
#90
b11 5
b1000 4
0!
b111 0
1(
#95
0(
#100
b100 5
1!
16
b1000 0
b11 7
1(
#105
0(
#110
b100 7
1!
06
b0 5
1(
1"
b0 '
b0 )
b0 9
#115
0(
#120
03
b0 7
b1 5
1(
0"
#125
0(
#130
03
b0 4
b1 5
b0 0
1!
1(
1$
#135
0(
#140
b10 5
0!
13
b1 7
1(
0$
#145
0(
#150
b1 4
b10 7
1(
#155
0(
#160
b10 4
b1 0
1(
#165
0(
#170
b11 4
b10 0
1(
#175
0(
#180
b100 4
b11 0
1(
#185
0(
#190
b101 4
b100 0
1(
#195
0(
#200
b110 4
b101 0
1(
#205
0(
#210
b111 4
b110 0
1(
#215
0(
#220
b11 5
b1000 4
b111 0
1(
#225
0(
#230
b100 5
b1000 0
b11 7
1(
#235
0(
#240
b0 5
1!
b100 7
1(
#245
0(
#250
b1 5
03
b0 7
1(
#255
0(
#260
b10 5
0!
13
b1 7
1(
#265
0(
#270
b1001 4
x!
b10 7
1(
#275
0(
#280
b1010 4
b1001 0
1(
#285
0(
#290
b1011 4
b1010 0
1(
#295
0(
#300
b1100 4
b1011 0
1(
#305
0(
#310
b1101 4
b1100 0
1(
#315
0(
#320
b1110 4
b1101 0
1(
#325
0(
#330
b1111 4
b1110 0
1(
#335
0(
#340
b0 4
b1111 0
1(
