FINAL/UART1_tester.v
module UART1_tester(
    output reg clk,
    output reg rst,
    output reg idle_bit,
    output reg start_bit,
    output reg [7:0] tx1,
    output reg stop_bit,
    input wire serial_out
);

    always begin
        #5 clk = ~clk; 
    end

    initial begin
        clk = 1;
        rst = 1;
        idle_bit = 1;
        start_bit = 1;
        tx1 = 8'b00000000;
        stop_bit = 0;

        #10 rst = 0;

        #10 idle_bit = 0; 
        start_bit = 0; 
        #10 start_bit = 1; tx1 = 8'b10101100; 
        #90 tx1 = 8'b0; 
        #10 stop_bit = 1; 
        #10 idle_bit = 1; stop_bit = 0; 
        #200 $finish;
    end

endmodule

FINAL/UART1_dut.v
module UART1_dut(
    input wire clk,
    input wire rst,
    input wire idle_bit,
    input wire start_bit,
    input wire [7:0] tx1,
    input wire stop_bit,
    output reg serial_out
);

    localparam IDLE = 3'b000,
               START = 3'b001,
               DATA = 3'b010,
               PARITY = 3'b011,
               STOP = 3'b100;

    reg [2:0] state, next_state;
    reg [7:0] data_register; 
    reg [3:0] contador;   
    reg parity_bit;    

    always @(posedge clk or posedge rst) begin
        if (rst) begin
            state <= IDLE;
            serial_out <= 1'b0;
            data_register <= 8'b0;
            contador <= 4'b0;
            parity_bit <= 1'b0;
        end else begin
            state <= next_state;

            case (state)
                IDLE: serial_out <= 1'b1; 
                START: serial_out <= 1'b0; 
                DATA: begin
                    serial_out <= data_register[0]; // BMS primero 
                    data_register <= {1'b0, data_register[7:1]}; // Shift right
                end
                PARITY: serial_out <= parity_bit;
                STOP: serial_out <= 1'b1; 
            endcase
        end
    end

    always @(*) begin

        next_state = state;

        case (state)
            IDLE: if (!idle_bit) next_state = START;
            START: if (!start_bit || !idle_bit) next_state = DATA;
            DATA: if (contador == 8) next_state = PARITY;
            PARITY: next_state = STOP;
            STOP: next_state = IDLE;
        endcase
    end

    // parity_bit
    always @(posedge clk or posedge rst) begin
        if (rst) begin
            parity_bit <= 1'b0;
        end else if (state == DATA && contador == 0) begin
            parity_bit <= ^tx1; 
        end
    end

    // Contador para DATA
    always @(posedge clk or posedge rst) begin
        if (rst) begin
            contador <= 4'b0;
        end else if (state == DATA) begin
            if (contador < 8) contador <= contador + 1;
        end else begin
            contador <= 4'b0;
        end
    end

endmodule

FINAL/UART1_tb.v
`include "UART1_dut.v"
`include "UART1_tester.v"

module UART1_tb;

    wire clk;
    wire rst;
    wire idle_bit;
    wire start_bit;
    wire [7:0] tx1;
    wire stop_bit;
    wire serial_out;

    UART1_dut dut (
        .clk(clk),
        .rst(rst),
        .idle_bit(idle_bit),
        .start_bit(start_bit),
        .tx1(tx1),
        .stop_bit(stop_bit),
        .serial_out(serial_out)
    );

    UART1_tester tester (
        .clk(clk),
        .rst(rst),
        .idle_bit(idle_bit),
        .start_bit(start_bit),
        .tx1(tx1),
        .stop_bit(stop_bit),
        .serial_out(serial_out)
    );

    initial begin
        $dumpfile("UART1_tb.vcd");
        $dumpvars(0, UART1_tb);
    end

endmodule

FINAL/UART1_tb.vcd
$date
	Sun Dec  1 00:04:29 2024
$end
$version
	Icarus Verilog
$end
$timescale
	1s
$end
$scope module UART1_tb $end
$var wire 8 ! tx1 [7:0] $end
$var wire 1 " stop_bit $end
$var wire 1 # start_bit $end
$var wire 1 $ serial_out $end
$var wire 1 % rst $end
$var wire 1 & idle_bit $end
$var wire 1 ' clk $end
$scope module dut $end
$var wire 8 ( tx1 [7:0] $end
$var wire 1 " stop_bit $end
$var wire 1 # start_bit $end
$var wire 1 % rst $end
$var wire 1 & idle_bit $end
$var wire 1 ' clk $end
$var parameter 3 ) DATA $end
$var parameter 3 * IDLE $end
$var parameter 3 + PARITY $end
$var parameter 3 , START $end
$var parameter 3 - STOP $end
$var reg 4 . contador [3:0] $end
$var reg 8 / data_register [7:0] $end
$var reg 3 0 next_state [2:0] $end
$var reg 1 1 parity_bit $end
$var reg 1 $ serial_out $end
$var reg 3 2 state [2:0] $end
$upscope $end
$scope module tester $end
$var wire 1 $ serial_out $end
$var reg 1 ' clk $end
$var reg 1 & idle_bit $end
$var reg 1 % rst $end
$var reg 1 # start_bit $end
$var reg 1 " stop_bit $end
$var reg 8 3 tx1 [7:0] $end
$upscope $end
$upscope $end
$enddefinitions $end
$comment Show the parameter values. $end
$dumpall
b100 -
b1 ,
b11 +
b0 *
b10 )
$end
#0
$dumpvars
b0 3
b0 2
01
b0 0
b0 /
b0 .
b0 (
1'
1&
1%
0$
1#
0"
b0 !
$end
#5
0'
#10
1$
1'
0%
#15
0'
#20
b1 2
b10 0
1'
0#
0&
#25
0'
#30
0$
b10 2
b10 0
1'
b10100100 !
b10100100 (
b10100100 3
1#
#35
0'
#40
11
b1 .
1'
#41
b0 !
b0 (
b0 3
#45
0'
#50
b10 .
1'
#51
1"
#55
0'
#60
b11 .
1'
#61
0"
1&
#65
0'
#70
b100 .
1'
#75
0'
#80
b101 .
1'
#85
0'
#90
b110 .
1'
#95
0'
#100
b111 .
1'
#105
0'
#110
b11 0
b1000 .
1'
#115
0'
#120
b100 0
b11 2
1'
#125
0'
#130
b0 0
b0 .
1$
b100 2
1'
#135
0'
#140
b0 2
1'
